fakts/__init__.py
fakts/cli/__init__.py
fakts/cli/advertise.py
fakts/cli/main.py
fakts/errors.py
fakts/fakts.py
fakts/grants/__init__.py
fakts/grants/env.py
fakts/grants/errors.py
fakts/grants/io/__init__.py
fakts/grants/io/qt/yaml.py
fakts/grants/io/toml.py
fakts/grants/io/yaml.py
fakts/grants/meta/__init__.py
fakts/grants/meta/cache.py
fakts/grants/meta/failsafe.py
fakts/grants/meta/parallel.py
fakts/grants/remote/__init__.py
fakts/grants/remote/base.py
fakts/grants/remote/builders.py
fakts/grants/remote/claimers/__init__.py
fakts/grants/remote/claimers/post.py
fakts/grants/remote/claimers/static.py
fakts/grants/remote/demanders/__init__.py
fakts/grants/remote/demanders/auto_save.py
fakts/grants/remote/demanders/cache.py
fakts/grants/remote/demanders/device_code.py
fakts/grants/remote/demanders/qt/__init__.py
fakts/grants/remote/demanders/qt/auto_save_token_widget.py
fakts/grants/remote/demanders/qt/qt_settings_token_store.py
fakts/grants/remote/demanders/redeem.py
fakts/grants/remote/demanders/retrieve.py
fakts/grants/remote/demanders/static.py
fakts/grants/remote/demanders/utils.py
fakts/grants/remote/discovery/__init__.py
fakts/grants/remote/discovery/advertised.py
fakts/grants/remote/discovery/auto_save.py
fakts/grants/remote/discovery/cache.py
fakts/grants/remote/discovery/qt/__init__.py
fakts/grants/remote/discovery/qt/auto_save_endpoint_widget.py
fakts/grants/remote/discovery/qt/qt_settings_endpoint_store.py
fakts/grants/remote/discovery/qt/selectable_beacon.py
fakts/grants/remote/discovery/static.py
fakts/grants/remote/discovery/utils.py
fakts/grants/remote/discovery/well_known.py
fakts/grants/remote/errors.py
fakts/grants/remote/models.py
fakts/models.py
fakts/utils.py
fakts-1.0.0.dist-info/METADATA
fakts-1.0.0.dist-info/WHEEL
fakts-1.0.0.dist-info/entry_points.txt
fakts-1.0.0.dist-info/RECORD
