Metadata-Version: 2.1
Name: fakts
Version: 1.0.0
Summary: asynchronous configuration provider ( tailored to support dynamic client-server relations)
License: CC BY-NC 3.0
Author: jhnnsrs
Author-email: jhnnsrs@gmail.com
Requires-Python: >=3.8,<4.0
Classifier: License :: Other/Proprietary License
Classifier: Programming Language :: Python :: 3
Classifier: Programming Language :: Python :: 3.8
Classifier: Programming Language :: Python :: 3.9
Classifier: Programming Language :: Python :: 3.10
Classifier: Programming Language :: Python :: 3.11
Classifier: Programming Language :: Python :: 3.12
Provides-Extra: cli
Provides-Extra: remote
Requires-Dist: PyYAML (>=6)
Requires-Dist: QtPy (>=2.0.1,<3.0.0)
Requires-Dist: aiohttp (>=3.8.2,<4.0.0) ; extra == "remote"
Requires-Dist: certifi (>2021) ; extra == "remote"
Requires-Dist: koil (>=1.0.0)
Requires-Dist: netifaces (>=0.11.0,<0.12.0) ; extra == "cli"
Requires-Dist: pydantic (>2)
Requires-Dist: rich_click (>=0.3) ; extra == "cli"
